{
  "generator-jhipster": {
    "applicationType": "gateway",
    "baseName": "gateway",
    "jhipsterVersion": "7.4.0",
    "skipUserManagement": false,
    "skipCheckLengthOfIdentifier": false,
    "skipFakeData": false,
    "jhiPrefix": "jhi",
    "entitySuffix": "",
    "dtoSuffix": "DTO",
    "testFrameworks": [],
    "blueprints": [],
    "otherModules": [],
    "pages": [],
    "creationTimestamp": 1645143377630,
    "serviceDiscoveryType": "eureka",
    "reactive": true,
    "authenticationType": "jwt",
    "packageName": "com.mycompany.myapp",
    "serverPort": "8080",
    "cacheProvider": "no",
    "enableHibernateCache": false,
    "databaseType": "sql",
    "devDatabaseType": "h2Memory",
    "prodDatabaseType": "mysql",
    "buildTool": "maven",
    "serverSideOptions": [],
    "websocket": false,
    "searchEngine": false,
    "messageBroker": false,
    "enableSwaggerCodegen": false,
    "clientFramework": "angularX",
    "withAdminUi": true,
    "clientTheme": "none",
    "enableTranslation": true,
    "nativeLanguage": "en",
    "monorepository": true,
    "skipCommitHook": true,
    "jwtSecretKey": "ZmY0ZjExY2U3OTdhZmI4YjZhNmYwZTlhMjBjMDYyOGU1ZTQwMDg1NTQ5ZTVjOWJjZjViYTdhOGI1YzczYmQ2MDUzYTE2MmQxYTVhNTI3YmJlMmZhZTQxMjE2ZmUwOTdkZjY0NTA4ODljOTJjMWFkYzZjOGYxMGExYTM1YjRmNTc=",
    "devServerPort": 4200,
    "clientPackageManager": "npm",
    "clientThemeVariant": "",
    "languages": ["en", "de"],
    "enableGradleEnterprise": false,
    "azureSpringCloudAppName": "gateway",
    "azureSpringCloudDeploymentType": "local",
    "entities": ["Todo"],
    "lastLiquibaseTimestamp": 1645239062000
  }
}
